[
    {
        "device": "device1",
        "status": "Error",
        "timestamp": "2023-06-29 11:57:38.808403"
    },
    {
        "device": "device2",
        "status": "OK",
        "timestamp": "2023-06-29 11:57:40.816777"
    },
    {
        "device": "device3",
        "status": "Error",
        "timestamp": "2023-06-29 11:57:42.821045"
    },
    {
        "device": "device4",
        "status": "OK",
        "timestamp": "2023-06-29 11:57:44.825207"
    },
    {
        "device": "device5",
        "status": "Error",
        "timestamp": "2023-06-29 11:57:46.833325"
    },
    {
        "device": "device6",
        "status": "OK",
        "timestamp": "2023-06-29 11:57:48.833995"
    },
    {
        "device": "device7",
        "status": "Error",
        "timestamp": "2023-06-29 11:57:50.848961"
    },
    {
        "device": "device8",
        "status": "OK",
        "timestamp": "2023-06-29 11:57:52.856257"
    },
    {
        "device": "device9",
        "status": "Error",
        "timestamp": "2023-06-29 11:57:54.864933"
    },
    {
        "device": "device10",
        "status": "OK",
        "timestamp": "2023-06-29 11:57:56.869019"
    }
]