[
    {
        "device": "device1",
        "status": "Error",
        "timestamp": "2023-06-29 09:54:11.449505"
    },
    {
        "device": "device2",
        "status": "OK",
        "timestamp": "2023-06-29 09:54:13.462258"
    },
    {
        "device": "device3",
        "status": "Error",
        "timestamp": "2023-06-29 09:54:15.474436"
    },
    {
        "device": "device4",
        "status": "OK",
        "timestamp": "2023-06-29 09:54:17.488988"
    },
    {
        "device": "device5",
        "status": "Error",
        "timestamp": "2023-06-29 09:54:19.492545"
    },
    {
        "device": "device6",
        "status": "OK",
        "timestamp": "2023-06-29 09:54:21.500536"
    },
    {
        "device": "device7",
        "status": "Error",
        "timestamp": "2023-06-29 09:54:23.503382"
    },
    {
        "device": "device8",
        "status": "OK",
        "timestamp": "2023-06-29 09:54:25.507772"
    },
    {
        "device": "device9",
        "status": "Error",
        "timestamp": "2023-06-29 09:54:27.518828"
    },
    {
        "device": "device10",
        "status": "OK",
        "timestamp": "2023-06-29 09:54:29.523031"
    }
]