[
    {
        "device": "device1",
        "status": "Error",
        "timestamp": "2023-06-29 12:01:52.652051"
    },
    {
        "device": "device2",
        "status": "OK",
        "timestamp": "2023-06-29 12:01:54.664358"
    },
    {
        "device": "device3",
        "status": "Error",
        "timestamp": "2023-06-29 12:01:56.670822"
    },
    {
        "device": "device4",
        "status": "OK",
        "timestamp": "2023-06-29 12:01:58.680947"
    },
    {
        "device": "device5",
        "status": "Error",
        "timestamp": "2023-06-29 12:02:00.695806"
    },
    {
        "device": "device6",
        "status": "OK",
        "timestamp": "2023-06-29 12:02:02.707142"
    },
    {
        "device": "device7",
        "status": "Error",
        "timestamp": "2023-06-29 12:02:04.721170"
    },
    {
        "device": "device8",
        "status": "OK",
        "timestamp": "2023-06-29 12:02:06.731827"
    },
    {
        "device": "device9",
        "status": "Error",
        "timestamp": "2023-06-29 12:02:08.747043"
    },
    {
        "device": "device10",
        "status": "OK",
        "timestamp": "2023-06-29 12:02:10.755104"
    }
]