[
    {
        "device": "device1",
        "status": "Error",
        "timestamp": "2023-06-29 10:19:34.444226"
    },
    {
        "device": "device2",
        "status": "OK",
        "timestamp": "2023-06-29 10:19:36.447495"
    },
    {
        "device": "device3",
        "status": "Error",
        "timestamp": "2023-06-29 10:19:38.454293"
    },
    {
        "device": "device4",
        "status": "OK",
        "timestamp": "2023-06-29 10:19:40.460614"
    },
    {
        "device": "device5",
        "status": "Error",
        "timestamp": "2023-06-29 10:19:42.464649"
    },
    {
        "device": "device6",
        "status": "OK",
        "timestamp": "2023-06-29 10:19:44.470769"
    },
    {
        "device": "device7",
        "status": "Error",
        "timestamp": "2023-06-29 10:19:46.479075"
    },
    {
        "device": "device8",
        "status": "OK",
        "timestamp": "2023-06-29 10:19:48.483474"
    },
    {
        "device": "device9",
        "status": "Error",
        "timestamp": "2023-06-29 10:19:50.490195"
    },
    {
        "device": "device10",
        "status": "OK",
        "timestamp": "2023-06-29 10:19:52.500260"
    }
]